setup.py
reportbot/__init__.py
reportbot/reportbot.py
reportbot.egg-info/PKG-INFO
reportbot.egg-info/SOURCES.txt
reportbot.egg-info/dependency_links.txt
reportbot.egg-info/not-zip-safe
reportbot.egg-info/requires.txt
reportbot.egg-info/top_level.txt