Metadata-Version: 1.0
Name: reportbot
Version: 0.1
Summary: report machine learning results to you on telegram
Home-page: https://github.com/dotannn/reportbot
Author: Dotan Asselmann
Author-email: dotan1988@gmail.com
License: MIT
Keywords: roc,sklearn,classification,report,ml
Platform: UNKNOWN
